krypto_gui_smalk/__init__.py
krypto_gui_smalk/__main__.py
krypto_gui_smalk/main.py
krypto_gui_smalk/resource_manager.py
krypto_gui_smalk/tk_inf.py
krypto_gui_smalk/assets/ico.png
krypto_gui_smalk-0.2.1.dist-info/licenses/LICENSE
krypto_gui_smalk-0.2.1.dist-info/METADATA
krypto_gui_smalk-0.2.1.dist-info/WHEEL
krypto_gui_smalk-0.2.1.dist-info/entry_points.txt
krypto_gui_smalk-0.2.1.dist-info/top_level.txt
krypto_gui_smalk-0.2.1.dist-info/RECORD
