Metadata-Version: 2.4
Name: krypto_gui_smalk
Version: 0.2.1
Summary: gui for smalk krypto testing .
Author-email: The220th <The220th@gmail.com>
License-Expression: MIT
Project-URL: Homepage, https://github.com/The220th/krypto_gui_smalk
Project-URL: Issues, https://github.com/The220th/krypto_gui_smalk/issues
Classifier: Programming Language :: Python :: 3
Classifier: Operating System :: POSIX :: Linux
Requires-Python: >=3.7
License-File: LICENSE
Requires-Dist: alerk_pack
Requires-Dist: ksupk
Dynamic: license-file
